pip_update/__init__.py
pip_update/__main__.py
pip_update/pip_update.py
pip_update-0.4.0.dist-info/DESCRIPTION.rst
pip_update-0.4.0.dist-info/METADATA
pip_update-0.4.0.dist-info/RECORD
pip_update-0.4.0.dist-info/WHEEL
pip_update-0.4.0.dist-info/entry_points.txt
pip_update-0.4.0.dist-info/metadata.json
pip_update-0.4.0.dist-info/top_level.txt
