Metadata-Version: 2.0
Name: pip-update
Version: 0.4.0
Summary: A current and update package list of environment extractor.
Home-page: https://github.com/gogobook/python-env-upgradable-packages-extractor
Author: gogobook
Author-email: o968041428@google.com
License: MIT License
Keywords: upgradable packages extractor
Platform: UNKNOWN
Classifier: Development Status :: 4 - Beta
Classifier: Environment :: Console
Classifier: Intended Audience :: Developers
Classifier: Operating System :: OS Independent
Classifier: Programming Language :: Python
Classifier: Programming Language :: Python :: 2
Classifier: Programming Language :: Python :: 2.7
Classifier: Programming Language :: Python :: 3
Classifier: Programming Language :: Python :: 3.5
Classifier: Programming Language :: Python :: 3.6
Requires-Dist: pip (>=9.0.1)
